json_and_validation/__init__.py
json_and_validation/json_validation.py
json_and_validation-1.0.0.dist-info/LICENSE
json_and_validation-1.0.0.dist-info/METADATA
json_and_validation-1.0.0.dist-info/WHEEL
json_and_validation-1.0.0.dist-info/top_level.txt
json_and_validation-1.0.0.dist-info/RECORD
