Metadata-Version: 2.1
Name: json-and-validation
Version: 1.0.0
Summary: A lightweight solution to validate JSON files and strings, in Python
Home-page: https://github.com/Whoeza/json_and_validation
Author: Whoeza
License: GNU GPLv3
Project-URL: Bug Tracker, https://github.com/Whoeza/json_and_validation/issues
Classifier: Intended Audience :: Developers
Classifier: License :: OSI Approved :: GNU General Public License v3 (GPLv3)
Classifier: Operating System :: OS Independent
Classifier: Programming Language :: Python :: 3
Requires-Python: >=3.10
License-File: LICENSE
